{
	"credit": "Made with Blockbench",
	"texture_size": [32, 32],
	"textures": {
		"0": "as:item/block/box2",
		"particle": "as:item/block/box2"
	},
	"elements": [
		{
			"from": [0, 0, 1],
			"to": [16, 8, 15],
			"rotation": {"angle": 0, "axis": "y", "origin": [0, 0, 1]},
			"faces": {
				"north": {"uv": [8, 0, 16, 4], "texture": "#0"},
				"east": {"uv": [8, 8, 15, 12], "texture": "#0"},
				"south": {"uv": [8, 4, 16, 8], "texture": "#0"},
				"west": {"uv": [8, 12, 15, 16], "texture": "#0"},
				"up": {"uv": [8, 7, 0, 0], "texture": "#0"},
				"down": {"uv": [8, 7, 0, 14], "texture": "#0"}
			}
		}
	],
	"display": {
		"thirdperson_righthand": {
			"translation": [0, 2.75, 0],
			"scale": [0.4, 0.4, 0.4]
		},
		"ground": {
			"scale": [0.3, 0.3, 0.3]
		},
		"gui": {
			"rotation": [30, -45, 0],
			"translation": [0, 2, 0],
			"scale": [0.7, 0.7, 0.7]
		}
	}
}